download_pbi_xmla/.env_example
download_pbi_xmla/__init__.py
download_pbi_xmla/download.py
download_pbi_xmla/example_config.json
download_pbi_xmla/main.py
download_pbi_xmla/run_download.py
download_pbi_xmla/setup_files.py
download_pbi_xmla/ssas_api.py
README.md
download_pbi_xmla-0.4.8.dist-info/entry_points.txt
download_pbi_xmla-0.4.8.dist-info/METADATA
download_pbi_xmla-0.4.8.dist-info/WHEEL
download_pbi_xmla-0.4.8.dist-info/RECORD
