Metadata-Version: 2.1
Name: download_pbi_xmla
Version: 0.4.8
Summary: A package to fetch and save Power BI tables via XMLA endpoint
Author: Danny Bharat
Author-email: dannybharat@arkimetrix.com
Requires-Python: >=3.9,<3.13
Classifier: Programming Language :: Python :: 3
Classifier: Programming Language :: Python :: 3.9
Classifier: Programming Language :: Python :: 3.10
Classifier: Programming Language :: Python :: 3.11
Classifier: Programming Language :: Python :: 3.12
Requires-Dist: msal (>=1.29.0,<2.0.0)
Requires-Dist: pandas (>=2.2.2,<3.0.0)
Requires-Dist: pyarrow (>=16.1.0,<17.0.0)
Requires-Dist: python-dotenv (>=1.0.1,<2.0.0)
Requires-Dist: pythonnet (>=3.0.3,<4.0.0)
